hello_world_pkg/__init__.py
appserver_sdk_hello_world_pkg-0.1.1.dist-info/METADATA
appserver_sdk_hello_world_pkg-0.1.1.dist-info/WHEEL
appserver_sdk_hello_world_pkg-0.1.1.dist-info/RECORD
