Metadata-Version: 2.3
Name: appserver-sdk-hello-world-pkg
Version: 0.1.1
Summary: Pacote exemplo que retorna hello world
License: MIT
Keywords: hello-world,example,appserver-sdk
Author: Appserver SDK
Author-email: suporte@apppserver.com.br
Requires-Python: >=3.11
Classifier: Development Status :: 4 - Beta
Classifier: Intended Audience :: Developers
Classifier: License :: OSI Approved :: MIT License
Classifier: Programming Language :: Python :: 3
Classifier: Programming Language :: Python :: 3.11
Classifier: Programming Language :: Python :: 3.12
Classifier: Programming Language :: Python :: 3.13
Project-URL: Documentation, https://github.com/appserver-sdk/hello_world_pkg#readme
Project-URL: Homepage, https://github.com/appserver-sdk/hello_world_pkg
Project-URL: Issues, https://github.com/appserver-sdk/hello_world_pkg/issues
Project-URL: Repository, https://github.com/appserver-sdk/hello_world_pkg
